src/__init__.py
src/historianstexttools/__init__.py
src/historianstexttools/chunk.py
src/historianstexttools/chunking.py
src/historianstexttools/cleantext.py
src/historianstexttools/dataloaders.py
src/historianstexttools/filemanipulation.py
src/historianstexttools/historianstexttools.py
src/historianstexttools/tester.py
historianstexttools-0.0.3.dist-info/METADATA
historianstexttools-0.0.3.dist-info/WHEEL
historianstexttools-0.0.3.dist-info/top_level.txt
historianstexttools-0.0.3.dist-info/RECORD
