Metadata-Version: 2.1
Name: historianstexttools
Version: 0.0.3
Summary: Common tools for historians to aid text analysis.
Home-page: UNKNOWN
Author: Christopher Thomas Goodwin
Author-email: <ctg7w6@gmail.com>
License: UNKNOWN
Keywords: python,historian,text,text-analysis
Platform: UNKNOWN
Classifier: Development Status :: 3 - Alpha
Classifier: Intended Audience :: Science/Research
Classifier: License :: OSI Approved :: MIT License
Classifier: Operating System :: OS Independent
Requires-Dist: nltk (>=3.8.1)
Requires-Dist: spacy (>=3.7.4)
